
{"took":3,"timed_out":false,"_shards":{"total":5,"successful":5,"failed":0},"hits":{"total":50159,"max_score":1.0,"hits":[{"_index":"ornl_label","_type":"label","_id":"03f12f2d-6eab-3dce-af13-971b8cf2e6cc","_score":1.0,"_source":{"has_label": false, "interesting": 0.25034579331655082, "created_at": "2016-07-06T22:29:34.454350", "label": false, "priority": 0.26384763236065001, "vector": [{"key": "topic-event_name|25", "value": 0.011363636363636369}, {"key": "topic-event_name|09", "value": 0.011363636363636369}, {"key": "topic-event_name|08", "value": 0.011363636363636369}, {"key": "topic-event_name|29", "value": 0.011363636363636369}, {"key": "topic-event_name|28", "value": 0.011363636363636369}, {"key": "topic-event_name|24", "value": 0.011363636363636369}, {"key": "topic-event_name|03", "value": 0.011363636363636369}, {"key": "topic-event_name|02", "value": 0.011363636363636369}, {"key": "topic-event_name|01", "value": 0.011363636363636369}, {"key": "topic-event_name|00", "value": 0.011363636363636369}, {"key": "topic-event_name|07", "value": 0.011363636363636369}, {"key": "topic-event_name|20", "value": 0.011363636363636369}, {"key": "topic-event_name|05", "value": 0.011363636363636369}, {"key": "topic-event_name|04", "value": 0.011363636363636369}, {"key": "topic-event_name|32", "value": 0.011363636363636369}, {"key": "topic-event_name|33", "value": 0.51136363636359727}, {"key": "topic-event_name|27", "value": 0.011363636363636369}, {"key": "topic-event_name|26", "value": 0.011363636363636369}, {"key": "topic-event_name|36", "value": 0.011363636363636369}, {"key": "topic-event_name|37", "value": 0.011363636363636369}, {"key": "topic-event_name|34", "value": 0.011363636363636369}, {"key": "topic-event_name|35", "value": 0.011363636363636369}, {"key": "topic-event_name|21", "value": 0.011363636363636369}, {"key": "topic-event_name|38", "value": 0.011363636363636369}, {"key": "topic-event_name|39", "value": 0.011363636363636369}, {"key": "topic-event_name|06", "value": 0.011363636363636369}, {"key": "topic-event_name|23", "value": 0.011363636363636369}, {"key": "cat|navy_not", "value": 1.0}, {"key": "topic-event_name|22", "value": 0.011363636363636369}, {"key": "event_name|P2P: BitTorrent File Transfer HandShaking", "value": 1.0}, {"key": "topic-event_name|30", "value": 0.011363636363636369}, {"key": "topic-event_name|18", "value": 0.011363636363636369}, {"key": "topic-event_name|19", "value": 0.011363636363636369}, {"key": "topic-event_name|31", "value": 0.011363636363636369}, {"key": "topic-event_name|10", "value": 0.011363636363636369}, {"key": "topic-event_name|11", "value": 0.011363636363636369}, {"key": "topic-event_name|12", "value": 0.011363636363636369}, {"key": "topic-event_name|13", "value": 0.011363636363636369}, {"key": "topic-event_name|14", "value": 0.011363636363636369}, {"key": "topic-event_name|15", "value": 0.011363636363636369}, {"key": "topic-event_name|16", "value": 0.011363636363636369}, {"key": "topic-event_name|17", "value": 0.011363636363636369}, {"key": "size|event_name", "value": 1.0}, {"key": "topic-event_name|43", "value": 0.011363636363636369}, {"key": "topic-event_name|42", "value": 0.011363636363675361}, {"key": "topic-event_name|41", "value": 0.011363636363636369}, {"key": "topic-event_name|40", "value": 0.011363636363636369}], "time": ["2015-04-24T09:00:00Z", "2015-04-24T10:00:00Z"], "anomaly": 0.26384763236065001, "row": ["1.161.54.139", "128.38.2.246", "NSTNORXNUSDAHL"]}},{"_index":"ornl_label","_type":"label","_id":"cb0d4da0-fdd8-38ea-8e70-4180e79f4df3","_score":1.0,"_source":{"has_label": false, "interesting": 0.22271462335705872, "created_at": "2016-07-06T22:29:35.218611", "label": false, "priority": 0.14747510047178053, "vector": [{"key": "topic-event_name|25", "value": 0.011363636363636369}, {"key": "topic-event_name|09", "value": 0.011363636363636369}, {"key": "topic-event_name|08", "value": 0.011363636363636369}, {"key": "topic-event_name|29", "value": 0.011363636363636369}, {"key": "topic-event_name|28", "value": 0.011363636363636369}, {"key": "topic-event_name|24", "value": 0.011363636363636369}, {"key": "topic-event_name|03", "value": 0.011363636363636369}, {"key": "topic-event_name|02", "value": 0.011363636363636369}, {"key": "topic-event_name|01", "value": 0.011363636363636369}, {"key": "topic-event_name|00", "value": 0.011363636363636369}, {"key": "topic-event_name|07", "value": 0.011363636363636369}, {"key": "topic-event_name|20", "value": 0.011363636363636369}, {"key": "topic-event_name|05", "value": 0.011363636363636369}, {"key": "topic-event_name|04", "value": 0.011363636363636369}, {"key": "topic-event_name|32", "value": 0.011363636363636369}, {"key": "topic-event_name|33", "value": 0.51136363636359727}, {"key": "topic-event_name|27", "value": 0.011363636363636369}, {"key": "topic-event_name|26", "value": 0.011363636363636369}, {"key": "topic-event_name|36", "value": 0.011363636363636369}, {"key": "topic-event_name|37", "value": 0.011363636363636369}, {"key": "topic-event_name|34", "value": 0.011363636363636369}, {"key": "topic-event_name|35", "value": 0.011363636363636369}, {"key": "topic-event_name|21", "value": 0.011363636363636369}, {"key": "topic-event_name|38", "value": 0.011363636363636369}, {"key": "topic-event_name|39", "value": 0.011363636363636369}, {"key": "topic-event_name|06", "value": 0.011363636363636369}, {"key": "topic-event_name|23", "value": 0.011363636363636369}, {"key": "cat|navy_not", "value": 1.0}, {"key": "topic-event_name|22", "value": 0.011363636363636369}, {"key": "event_name|P2P: BitTorrent File Transfer HandShaking", "value": 1.0}, {"key": "topic-event_name|30", "value": 0.011363636363636369}, {"key": "topic-event_name|18", "value": 0.011363636363636369}, {"key": "topic-event_name|19", "value": 0.011363636363636369}, {"key": "topic-event_name|31", "value": 0.011363636363636369}, {"key": "topic-event_name|10", "value": 0.011363636363636369}, {"key": "topic-event_name|11", "value": 0.011363636363636369}, {"key": "topic-event_name|12", "value": 0.011363636363636369}, {"key": "topic-event_name|13", "value": 0.011363636363636369}, {"key": "topic-event_name|14", "value": 0.011363636363636369}, {"key": "topic-event_name|15", "value": 0.011363636363636369}, {"key": "topic-event_name|16", "value": 0.011363636363636369}, {"key": "topic-event_name|17", "value": 0.011363636363636369}, {"key": "size|event_name", "value": 1.0}, {"key": "topic-event_name|43", "value": 0.011363636363636369}, {"key": "topic-event_name|42", "value": 0.011363636363675361}, {"key": "topic-event_name|41", "value": 0.011363636363636369}, {"key": "topic-event_name|40", "value": 0.011363636363636369}], "time": ["2015-04-24T09:00:00Z", "2015-04-24T10:00:00Z"], "anomaly": 0.14747510047178053, "row": ["1.169.183.61", "129.190.253.3", "NSTNORXNUSNUWC"]}},{"_index":"ornl_label","_type":"label","_id":"93c30e58-353f-38c7-9be4-8ead623dba81","_score":1.0,"_source":{"has_label": false, "interesting": 0.20255065239644765, "created_at": "2016-07-06T22:29:36.423434", "label": false, "priority": 0.1488729687226979, "vector": [{"key": "topic-event_name|25", "value": 0.011363636363636369}, {"key": "topic-event_name|09", "value": 0.011363636363636369}, {"key": "topic-event_name|08", "value": 0.011363636363636369}, {"key": "topic-event_name|29", "value": 0.011363636363636369}, {"key": "topic-event_name|28", "value": 0.011363636363636369}, {"key": "topic-event_name|24", "value": 0.011363636363636369}, {"key": "topic-event_name|03", "value": 0.011363636363636369}, {"key": "topic-event_name|02", "value": 0.011363636363636369}, {"key": "topic-event_name|01", "value": 0.011363636363636369}, {"key": "topic-event_name|00", "value": 0.011363636363636369}, {"key": "topic-event_name|07", "value": 0.011363636363636369}, {"key": "topic-event_name|20", "value": 0.011363636363636369}, {"key": "topic-event_name|05", "value": 0.011363636363636369}, {"key": "topic-event_name|04", "value": 0.011363636363636369}, {"key": "topic-event_name|32", "value": 0.011363636363636369}, {"key": "topic-event_name|33", "value": 0.51136363636359727}, {"key": "topic-event_name|27", "value": 0.011363636363636369}, {"key": "topic-event_name|26", "value": 0.011363636363636369}, {"key": "topic-event_name|36", "value": 0.011363636363636369}, {"key": "topic-event_name|37", "value": 0.011363636363636369}, {"key": "topic-event_name|34", "value": 0.011363636363636369}, {"key": "topic-event_name|35", "value": 0.011363636363636369}, {"key": "topic-event_name|21", "value": 0.011363636363636369}, {"key": "topic-event_name|38", "value": 0.011363636363636369}, {"key": "topic-event_name|39", "value": 0.011363636363636369}, {"key": "topic-event_name|06", "value": 0.011363636363636369}, {"key": "topic-event_name|23", "value": 0.011363636363636369}, {"key": "cat|navy_not", "value": 1.0}, {"key": "topic-event_name|22", "value": 0.011363636363636369}, {"key": "event_name|P2P: BitTorrent File Transfer HandShaking", "value": 1.0}, {"key": "topic-event_name|30", "value": 0.011363636363636369}, {"key": "topic-event_name|18", "value": 0.011363636363636369}, {"key": "topic-event_name|19", "value": 0.011363636363636369}, {"key": "topic-event_name|31", "value": 0.011363636363636369}, {"key": "topic-event_name|10", "value": 0.011363636363636369}, {"key": "topic-event_name|11", "value": 0.011363636363636369}, {"key": "topic-event_name|12", "value": 0.011363636363636369}, {"key": "topic-event_name|13", "value": 0.011363636363636369}, {"key": "topic-event_name|14", "value": 0.011363636363636369}, {"key": "topic-event_name|15", "value": 0.011363636363636369}, {"key": "topic-event_name|16", "value": 0.011363636363636369}, {"key": "topic-event_name|17", "value": 0.011363636363636369}, {"key": "size|event_name", "value": 1.0}, {"key": "topic-event_name|43", "value": 0.011363636363636369}, {"key": "topic-event_name|42", "value": 0.011363636363675361}, {"key": "topic-event_name|41", "value": 0.011363636363636369}, {"key": "topic-event_name|40", "value": 0.011363636363636369}], "time": ["2015-04-24T09:00:00Z", "2015-04-24T10:00:00Z"], "anomaly": 0.1488729687226979, "row": ["1.214.49.29", "163.251.111.10", "NSTPACONKRCHIN"]}},{"_index":"ornl_label","_type":"label","_id":"cbf86fad-8e64-359f-a783-03e52c934945","_score":1.0,"_source":{"has_label": false, "interesting": 0.3838424186682613, "created_at": "2016-07-06T22:29:37.979417", "label": false, "priority": 0.14869823519133321, "vector": [{"key": "topic-event_name|25", "value": 0.011363636363636369}, {"key": "topic-event_name|09", "value": 0.011363636363636369}, {"key": "topic-event_name|08", "value": 0.011363636363636369}, {"key": "topic-event_name|29", "value": 0.011363636363636369}, {"key": "topic-event_name|28", "value": 0.011363636363636369}, {"key": "topic-event_name|24", "value": 0.011363636363636369}, {"key": "topic-event_name|03", "value": 0.011363636363636369}, {"key": "topic-event_name|02", "value": 0.011363636363636369}, {"key": "topic-event_name|01", "value": 0.011363636363636369}, {"key": "topic-event_name|00", "value": 0.011363636363636369}, {"key": "topic-event_name|07", "value": 0.011363636363636369}, {"key": "topic-event_name|20", "value": 0.011363636363636369}, {"key": "topic-event_name|05", "value": 0.011363636363636369}, {"key": "topic-event_name|04", "value": 0.011363636363636369}, {"key": "topic-event_name|32", "value": 0.011363636363636369}, {"key": "topic-event_name|33", "value": 0.51136363636359727}, {"key": "topic-event_name|27", "value": 0.011363636363636369}, {"key": "topic-event_name|26", "value": 0.011363636363636369}, {"key": "topic-event_name|36", "value": 0.011363636363636369}, {"key": "topic-event_name|37", "value": 0.011363636363636369}, {"key": "topic-event_name|34", "value": 0.011363636363636369}, {"key": "topic-event_name|35", "value": 0.011363636363636369}, {"key": "topic-event_name|21", "value": 0.011363636363636369}, {"key": "topic-event_name|38", "value": 0.011363636363636369}, {"key": "topic-event_name|39", "value": 0.011363636363636369}, {"key": "topic-event_name|06", "value": 0.011363636363636369}, {"key": "topic-event_name|23", "value": 0.011363636363636369}, {"key": "cat|navy_not", "value": 1.0}, {"key": "topic-event_name|22", "value": 0.011363636363636369}, {"key": "event_name|P2P: BitTorrent File Transfer HandShaking", "value": 1.0}, {"key": "topic-event_name|30", "value": 0.011363636363636369}, {"key": "topic-event_name|18", "value": 0.011363636363636369}, {"key": "topic-event_name|19", "value": 0.011363636363636369}, {"key": "topic-event_name|31", "value": 0.011363636363636369}, {"key": "topic-event_name|10", "value": 0.011363636363636369}, {"key": "topic-event_name|11", "value": 0.011363636363636369}, {"key": "topic-event_name|12", "value": 0.011363636363636369}, {"key": "topic-event_name|13", "value": 0.011363636363636369}, {"key": "topic-event_name|14", "value": 0.011363636363636369}, {"key": "topic-event_name|15", "value": 0.011363636363636369}, {"key": "topic-event_name|16", "value": 0.011363636363636369}, {"key": "topic-event_name|17", "value": 0.011363636363636369}, {"key": "size|event_name", "value": 1.0}, {"key": "topic-event_name|43", "value": 0.011363636363636369}, {"key": "topic-event_name|42", "value": 0.011363636363675361}, {"key": "topic-event_name|41", "value": 0.011363636363636369}, {"key": "topic-event_name|40", "value": 0.011363636363636369}], "time": ["2015-04-24T09:00:00Z", "2015-04-24T10:00:00Z"], "anomaly": 0.14869823519133321, "row": ["1.242.137.87", "160.107.188.80", "NSTNORXNUSPAXR"]}},{"_index":"ornl_label","_type":"label","_id":"02c5a26b-d2dd-3f99-a0e7-da43a61eb876","_score":1.0,"_source":{"has_label": false, "interesting": 0.19701998849174795, "created_at": "2016-07-06T22:29:38.208535", "label": false, "priority": 0.26332343176655598, "vector": [{"key": "topic-event_name|25", "value": 0.011363636363636369}, {"key": "topic-event_name|09", "value": 0.011363636363636369}, {"key": "topic-event_name|08", "value": 0.011363636363636369}, {"key": "topic-event_name|29", "value": 0.011363636363636369}, {"key": "topic-event_name|28", "value": 0.011363636363636369}, {"key": "topic-event_name|24", "value": 0.011363636363636369}, {"key": "topic-event_name|03", "value": 0.011363636363636369}, {"key": "topic-event_name|02", "value": 0.011363636363636369}, {"key": "topic-event_name|01", "value": 0.011363636363636369}, {"key": "topic-event_name|00", "value": 0.011363636363636369}, {"key": "topic-event_name|07", "value": 0.011363636363636369}, {"key": "topic-event_name|20", "value": 0.011363636363636369}, {"key": "topic-event_name|05", "value": 0.011363636363636369}, {"key": "topic-event_name|04", "value": 0.011363636363636369}, {"key": "topic-event_name|32", "value": 0.011363636363636369}, {"key": "topic-event_name|33", "value": 0.51136363636359727}, {"key": "topic-event_name|27", "value": 0.011363636363636369}, {"key": "topic-event_name|26", "value": 0.011363636363636369}, {"key": "topic-event_name|36", "value": 0.011363636363636369}, {"key": "topic-event_name|37", "value": 0.011363636363636369}, {"key": "topic-event_name|34", "value": 0.011363636363636369}, {"key": "topic-event_name|35", "value": 0.011363636363636369}, {"key": "topic-event_name|21", "value": 0.011363636363636369}, {"key": "topic-event_name|38", "value": 0.011363636363636369}, {"key": "topic-event_name|39", "value": 0.011363636363636369}, {"key": "topic-event_name|06", "value": 0.011363636363636369}, {"key": "topic-event_name|23", "value": 0.011363636363636369}, {"key": "cat|navy_not", "value": 1.0}, {"key": "topic-event_name|22", "value": 0.011363636363636369}, {"key": "event_name|P2P: BitTorrent File Transfer HandShaking", "value": 1.0}, {"key": "topic-event_name|30", "value": 0.011363636363636369}, {"key": "topic-event_name|18", "value": 0.011363636363636369}, {"key": "topic-event_name|19", "value": 0.011363636363636369}, {"key": "topic-event_name|31", "value": 0.011363636363636369}, {"key": "topic-event_name|10", "value": 0.011363636363636369}, {"key": "topic-event_name|11", "value": 0.011363636363636369}, {"key": "topic-event_name|12", "value": 0.011363636363636369}, {"key": "topic-event_name|13", "value": 0.011363636363636369}, {"key": "topic-event_name|14", "value": 0.011363636363636369}, {"key": "topic-event_name|15", "value": 0.011363636363636369}, {"key": "topic-event_name|16", "value": 0.011363636363636369}, {"key": "topic-event_name|17", "value": 0.011363636363636369}, {"key": "size|event_name", "value": 1.0}, {"key": "topic-event_name|43", "value": 0.011363636363636369}, {"key": "topic-event_name|42", "value": 0.011363636363675361}, {"key": "topic-event_name|41", "value": 0.011363636363636369}, {"key": "topic-event_name|40", "value": 0.011363636363636369}], "time": ["2015-04-24T09:00:00Z", "2015-04-24T10:00:00Z"], "anomaly": 0.26332343176655598, "row": ["1.246.213.118", "128.38.81.138", "NSTNORXNUSDAHL"]}},{"_index":"ornl_label","_type":"label","_id":"89a2a322-5457-3dc7-bbdb-b289883d1673","_score":1.0,"_source":{"has_label": false, "interesting": 0.47117609759273316, "created_at": "2016-07-06T22:29:38.906651", "label": false, "priority": 0.14904770225406255, "vector": [{"key": "topic-event_name|25", "value": 0.011363636363636369}, {"key": "topic-event_name|09", "value": 0.011363636363636369}, {"key": "topic-event_name|08", "value": 0.011363636363636369}, {"key": "topic-event_name|29", "value": 0.011363636363636369}, {"key": "topic-event_name|28", "value": 0.011363636363636369}, {"key": "topic-event_name|24", "value": 0.011363636363636369}, {"key": "topic-event_name|03", "value": 0.011363636363636369}, {"key": "topic-event_name|02", "value": 0.011363636363636369}, {"key": "topic-event_name|01", "value": 0.011363636363636369}, {"key": "topic-event_name|00", "value": 0.011363636363636369}, {"key": "topic-event_name|07", "value": 0.011363636363636369}, {"key": "topic-event_name|20", "value": 0.011363636363636369}, {"key": "topic-event_name|05", "value": 0.011363636363636369}, {"key": "topic-event_name|04", "value": 0.011363636363636369}, {"key": "topic-event_name|32", "value": 0.011363636363636369}, {"key": "topic-event_name|33", "value": 0.51136363636359727}, {"key": "topic-event_name|27", "value": 0.011363636363636369}, {"key": "topic-event_name|26", "value": 0.011363636363636369}, {"key": "topic-event_name|36", "value": 0.011363636363636369}, {"key": "topic-event_name|37", "value": 0.011363636363636369}, {"key": "topic-event_name|34", "value": 0.011363636363636369}, {"key": "topic-event_name|35", "value": 0.011363636363636369}, {"key": "topic-event_name|21", "value": 0.011363636363636369}, {"key": "topic-event_name|38", "value": 0.011363636363636369}, {"key": "topic-event_name|39", "value": 0.011363636363636369}, {"key": "topic-event_name|06", "value": 0.011363636363636369}, {"key": "topic-event_name|23", "value": 0.011363636363636369}, {"key": "cat|navy_not", "value": 1.0}, {"key": "topic-event_name|22", "value": 0.011363636363636369}, {"key": "event_name|P2P: BitTorrent File Transfer HandShaking", "value": 1.0}, {"key": "topic-event_name|30", "value": 0.011363636363636369}, {"key": "topic-event_name|18", "value": 0.011363636363636369}, {"key": "topic-event_name|19", "value": 0.011363636363636369}, {"key": "topic-event_name|31", "value": 0.011363636363636369}, {"key": "topic-event_name|10", "value": 0.011363636363636369}, {"key": "topic-event_name|11", "value": 0.011363636363636369}, {"key": "topic-event_name|12", "value": 0.011363636363636369}, {"key": "topic-event_name|13", "value": 0.011363636363636369}, {"key": "topic-event_name|14", "value": 0.011363636363636369}, {"key": "topic-event_name|15", "value": 0.011363636363636369}, {"key": "topic-event_name|16", "value": 0.011363636363636369}, {"key": "topic-event_name|17", "value": 0.011363636363636369}, {"key": "size|event_name", "value": 1.0}, {"key": "topic-event_name|43", "value": 0.011363636363636369}, {"key": "topic-event_name|42", "value": 0.011363636363675361}, {"key": "topic-event_name|41", "value": 0.011363636363636369}, {"key": "topic-event_name|40", "value": 0.011363636363636369}], "time": ["2015-04-24T09:00:00Z", "2015-04-24T10:00:00Z"], "anomaly": 0.14904770225406255, "row": ["1.64.166.103", "128.38.109.44", "NSTNORXNUSDAHL"]}},{"_index":"ornl_label","_type":"label","_id":"3eadec6e-765a-361d-9d9c-e0c5d9fb3fba","_score":1.0,"_source":{"has_label": false, "interesting": 0.7664663192888409, "created_at": "2016-07-06T22:29:39.021795", "label": false, "priority": 0.070068146077232218, "vector": [{"key": "topic-event_name|25", "value": 0.011363636365176242}, {"key": "topic-event_name|09", "value": 0.011363636365176242}, {"key": "topic-event_name|08", "value": 0.011363636365176242}, {"key": "topic-event_name|29", "value": 0.011363636365176242}, {"key": "topic-event_name|28", "value": 0.011363636365176242}, {"key": "topic-event_name|24", "value": 0.011363636365176242}, {"key": "topic-event_name|03", "value": 0.011363636365176242}, {"key": "topic-event_name|02", "value": 0.011363636365176242}, {"key": "topic-event_name|01", "value": 0.011363636365176242}, {"key": "topic-event_name|00", "value": 0.011363636365176242}, {"key": "topic-event_name|07", "value": 0.011363636365176242}, {"key": "topic-event_name|20", "value": 0.011363636365176242}, {"key": "topic-event_name|05", "value": 0.011363636365176242}, {"key": "topic-event_name|04", "value": 0.51136363629742154}, {"key": "topic-event_name|32", "value": 0.011363636365176242}, {"key": "topic-event_name|33", "value": 0.011363636365176242}, {"key": "topic-event_name|27", "value": 0.011363636365176242}, {"key": "topic-event_name|26", "value": 0.011363636365176242}, {"key": "topic-event_name|36", "value": 0.011363636365176242}, {"key": "topic-event_name|37", "value": 0.011363636365176242}, {"key": "topic-event_name|34", "value": 0.011363636365176242}, {"key": "topic-event_name|35", "value": 0.011363636365176242}, {"key": "topic-event_name|21", "value": 0.011363636365176242}, {"key": "topic-event_name|38", "value": 0.011363636365176242}, {"key": "topic-event_name|39", "value": 0.011363636365176242}, {"key": "topic-event_name|06", "value": 0.011363636365176242}, {"key": "topic-event_name|23", "value": 0.011363636365176242}, {"key": "cat|navy_not", "value": 1.0}, {"key": "topic-event_name|22", "value": 0.011363636365176242}, {"key": "topic-event_name|30", "value": 0.011363636365176242}, {"key": "topic-event_name|18", "value": 0.011363636365176242}, {"key": "topic-event_name|19", "value": 0.011363636365176242}, {"key": "topic-event_name|31", "value": 0.011363636365176242}, {"key": "event_name|P2P: Torrent uTP BEP-29 Traffic Detected", "value": 1.0}, {"key": "topic-event_name|10", "value": 0.011363636365176242}, {"key": "topic-event_name|11", "value": 0.011363636365176242}, {"key": "topic-event_name|12", "value": 0.011363636365176242}, {"key": "topic-event_name|13", "value": 0.011363636365176242}, {"key": "topic-event_name|14", "value": 0.011363636365176242}, {"key": "topic-event_name|15", "value": 0.011363636365176242}, {"key": "topic-event_name|16", "value": 0.011363636365176242}, {"key": "topic-event_name|17", "value": 0.011363636365176242}, {"key": "size|event_name", "value": 1.0}, {"key": "topic-event_name|43", "value": 0.011363636365176242}, {"key": "topic-event_name|42", "value": 0.011363636365176242}, {"key": "topic-event_name|41", "value": 0.011363636365176242}, {"key": "topic-event_name|40", "value": 0.011363636365176242}], "time": ["2015-04-24T09:00:00Z", "2015-04-24T10:00:00Z"], "anomaly": 0.070068146077232218, "row": ["1.9.97.25", "205.95.26.225", "NSTPACITUSWAHI"]}},{"_index":"ornl_label","_type":"label","_id":"0fb2adda-de75-3c73-beb2-a93f246f0dbb","_score":1.0,"_source":{"has_label": false, "interesting": 0.12933353735317377, "created_at": "2016-07-06T22:29:39.811264", "label": false, "priority": 0.92713611742093305, "vector": [{"key": "topic-event_name|25", "value": 0.0045454545454545912}, {"key": "topic-event_name|09", "value": 0.0045454545454545912}, {"key": "topic-event_name|08", "value": 0.12102695885619263}, {"key": "topic-event_name|29", "value": 0.0045454545454545912}, {"key": "topic-event_name|28", "value": 0.0045454545454545912}, {"key": "topic-event_name|24", "value": 0.0045454545454545912}, {"key": "topic-event_name|03", "value": 0.0045454545454545912}, {"key": "topic-event_name|02", "value": 0.0045454545454545912}, {"key": "topic-event_name|01", "value": 0.0045454545454545912}, {"key": "topic-event_name|00", "value": 0.0045454545454545912}, {"key": "topic-event_name|07", "value": 0.12102695885619263}, {"key": "topic-event_name|20", "value": 0.0045454545454545912}, {"key": "topic-event_name|05", "value": 0.0045454545454545912}, {"key": "topic-event_name|04", "value": 0.0045454545454545912}, {"key": "topic-event_name|32", "value": 0.0045454545454545912}, {"key": "topic-event_name|33", "value": 0.0045454545454545912}, {"key": "topic-event_name|27", "value": 0.0045454545454545912}, {"key": "topic-event_name|26", "value": 0.0045454545454545912}, {"key": "topic-event_name|36", "value": 0.0045454545454545912}, {"key": "topic-event_name|37", "value": 0.0045454545454545912}, {"key": "topic-event_name|34", "value": 0.0045454545454545912}, {"key": "topic-event_name|35", "value": 0.0045454545454545912}, {"key": "topic-event_name|21", "value": 0.0045454545454545912}, {"key": "topic-event_name|38", "value": 0.0045454545454545912}, {"key": "topic-event_name|39", "value": 0.0045454545454545912}, {"key": "topic-event_name|06", "value": 0.0045454545454545912}, {"key": "topic-event_name|23", "value": 0.0045454545454545912}, {"key": "topic-event_name|22", "value": 0.0045454545454545912}, {"key": "event_name|ICMP: Netmask Request", "value": 2.0}, {"key": "cat|private_private", "value": 1.0}, {"key": "topic-event_name|30", "value": 0.0045454545454545912}, {"key": "topic-event_name|18", "value": 0.0045454545454545912}, {"key": "topic-event_name|19", "value": 0.0045454545454545912}, {"key": "topic-event_name|31", "value": 0.0045454545454545912}, {"key": "topic-event_name|10", "value": 0.0045454545454545912}, {"key": "topic-event_name|11", "value": 0.0045454545454545912}, {"key": "topic-event_name|12", "value": 0.0045454545454545912}, {"key": "topic-event_name|13", "value": 0.4551009416132385}, {"key": "topic-event_name|14", "value": 0.0045454545454545912}, {"key": "topic-event_name|15", "value": 0.12102695885619263}, {"key": "topic-event_name|16", "value": 0.0045454545454545912}, {"key": "topic-event_name|17", "value": 0.0045454545454545912}, {"key": "size|event_name", "value": 4.0}, {"key": "topic-event_name|43", "value": 0.0045454545454545912}, {"key": "topic-event_name|42", "value": 0.0045454545454545912}, {"key": "topic-event_name|41", "value": 0.0045454545454545912}, {"key": "topic-event_name|40", "value": 0.0045454545454545912}, {"key": "event_name|ICMP: Timestamp Probe", "value": 2.0}, {"key": "entropy|event_name", "value": 0.69314718055994529}], "time": ["2015-04-24T09:00:00Z", "2015-04-24T10:00:00Z"], "anomaly": 0.92713611742093305, "row": ["10.0.0.125", "192.168.0.141", "NSTNORXNUSNAVO"]}},{"_index":"ornl_label","_type":"label","_id":"8623a2c8-cb4e-30b3-90e7-cdf312c2847c","_score":1.0,"_source":{"has_label": false, "interesting": 0.54839903550185665, "created_at": "2016-07-06T22:29:40.653344", "label": false, "priority": 0.63078804822645462, "vector": [{"key": "event_name|TCP: SYN Port Scan", "value": 1.0}, {"key": "topic-event_name|25", "value": 0.011363636363636449}, {"key": "topic-event_name|09", "value": 0.011363636363636449}, {"key": "topic-event_name|08", "value": 0.17803030303030187}, {"key": "topic-event_name|29", "value": 0.011363636363636449}, {"key": "topic-event_name|28", "value": 0.011363636363636449}, {"key": "topic-event_name|24", "value": 0.011363636363636449}, {"key": "topic-event_name|03", "value": 0.011363636363636449}, {"key": "topic-event_name|02", "value": 0.011363636363636449}, {"key": "topic-event_name|01", "value": 0.011363636363636449}, {"key": "topic-event_name|00", "value": 0.011363636363636449}, {"key": "topic-event_name|07", "value": 0.17803030303030187}, {"key": "topic-event_name|20", "value": 0.011363636363636449}, {"key": "topic-event_name|05", "value": 0.011363636363636449}, {"key": "topic-event_name|04", "value": 0.011363636363636449}, {"key": "topic-event_name|32", "value": 0.011363636363636449}, {"key": "topic-event_name|33", "value": 0.011363636363636449}, {"key": "topic-event_name|27", "value": 0.011363636363636449}, {"key": "topic-event_name|26", "value": 0.011363636363636449}, {"key": "topic-event_name|36", "value": 0.011363636363636449}, {"key": "topic-event_name|37", "value": 0.011363636363636449}, {"key": "topic-event_name|34", "value": 0.011363636363636449}, {"key": "topic-event_name|35", "value": 0.011363636363636449}, {"key": "topic-event_name|21", "value": 0.011363636363636449}, {"key": "topic-event_name|38", "value": 0.011363636363636449}, {"key": "topic-event_name|39", "value": 0.011363636363636449}, {"key": "topic-event_name|06", "value": 0.011363636363636449}, {"key": "topic-event_name|23", "value": 0.011363636363636449}, {"key": "topic-event_name|22", "value": 0.011363636363636449}, {"key": "cat|private_private", "value": 1.0}, {"key": "topic-event_name|30", "value": 0.011363636363636449}, {"key": "topic-event_name|18", "value": 0.011363636363636449}, {"key": "topic-event_name|19", "value": 0.011363636363636449}, {"key": "topic-event_name|31", "value": 0.011363636363636449}, {"key": "topic-event_name|10", "value": 0.011363636363636449}, {"key": "topic-event_name|11", "value": 0.011363636363636449}, {"key": "topic-event_name|12", "value": 0.011363636363636449}, {"key": "topic-event_name|13", "value": 0.011363636363636449}, {"key": "topic-event_name|14", "value": 0.011363636363636449}, {"key": "topic-event_name|15", "value": 0.17803030303030187}, {"key": "topic-event_name|16", "value": 0.011363636363636449}, {"key": "topic-event_name|17", "value": 0.011363636363636449}, {"key": "size|event_name", "value": 1.0}, {"key": "topic-event_name|43", "value": 0.011363636363636449}, {"key": "topic-event_name|42", "value": 0.011363636363636449}, {"key": "topic-event_name|41", "value": 0.011363636363636449}, {"key": "topic-event_name|40", "value": 0.011363636363636449}], "time": ["2015-04-24T09:00:00Z", "2015-04-24T10:00:00Z"], "anomaly": 0.63078804822645462, "row": ["10.0.0.125", "192.168.0.153", "NSTNORXNUSNAVO"]}},{"_index":"ornl_label","_type":"label","_id":"0158dde8-08eb-317d-aadc-3b7ed2849ac6","_score":1.0,"_source":{"has_label": false, "interesting": 0.30488112759371166, "created_at": "2016-07-06T22:29:41.254403", "label": false, "priority": 0.95596715009610345, "vector": [{"key": "event_name|TCP: SYN Port Scan", "value": 1.0}, {"key": "topic-event_name|25", "value": 0.0037878787878788283}, {"key": "topic-event_name|09", "value": 0.0037878787878788283}, {"key": "topic-event_name|08", "value": 0.16484841023305385}, {"key": "topic-event_name|29", "value": 0.0037878787878788283}, {"key": "topic-event_name|28", "value": 0.0037878787878788283}, {"key": "topic-event_name|24", "value": 0.0037878787878788283}, {"key": "topic-event_name|03", "value": 0.0037878787878788283}, {"key": "topic-event_name|02", "value": 0.0037878787878788283}, {"key": "topic-event_name|01", "value": 0.0037878787878788283}, {"key": "topic-event_name|00", "value": 0.0037878787878788283}, {"key": "topic-event_name|07", "value": 0.16484841023305385}, {"key": "topic-event_name|20", "value": 0.0037878787878788283}, {"key": "topic-event_name|05", "value": 0.0037878787878788283}, {"key": "topic-event_name|04", "value": 0.0037878787878788283}, {"key": "topic-event_name|32", "value": 0.0037878787878788283}, {"key": "topic-event_name|33", "value": 0.0037878787878788283}, {"key": "topic-event_name|27", "value": 0.0037878787878788283}, {"key": "topic-event_name|26", "value": 0.0037878787878788283}, {"key": "topic-event_name|36", "value": 0.0037878787878788283}, {"key": "topic-event_name|37", "value": 0.0037878787878788283}, {"key": "topic-event_name|34", "value": 0.0037878787878788283}, {"key": "topic-event_name|35", "value": 0.0037878787878788283}, {"key": "topic-event_name|21", "value": 0.0037878787878788283}, {"key": "topic-event_name|38", "value": 0.0037878787878788283}, {"key": "topic-event_name|39", "value": 0.0037878787878788283}, {"key": "topic-event_name|06", "value": 0.0037878787878788283}, {"key": "topic-event_name|23", "value": 0.0037878787878788283}, {"key": "topic-event_name|22", "value": 0.0037878787878788283}, {"key": "event_name|ICMP: Netmask Request", "value": 2.0}, {"key": "cat|private_private", "value": 1.0}, {"key": "topic-event_name|30", "value": 0.0037878787878788283}, {"key": "topic-event_name|18", "value": 0.0037878787878788283}, {"key": "topic-event_name|19", "value": 0.0037878787878788283}, {"key": "topic-event_name|31", "value": 0.0037878787878788283}, {"key": "topic-event_name|10", "value": 0.0037878787878788283}, {"key": "topic-event_name|11", "value": 0.0037878787878788283}, {"key": "topic-event_name|12", "value": 0.0037878787878788283}, {"key": "topic-event_name|13", "value": 0.35393961778568522}, {"key": "topic-event_name|14", "value": 0.0037878787878788283}, {"key": "topic-event_name|15", "value": 0.16484841023305385}, {"key": "topic-event_name|16", "value": 0.0037878787878788283}, {"key": "topic-event_name|17", "value": 0.0037878787878788283}, {"key": "size|event_name", "value": 5.0}, {"key": "topic-event_name|43", "value": 0.0037878787878788283}, {"key": "topic-event_name|42", "value": 0.0037878787878788283}, {"key": "topic-event_name|41", "value": 0.0037878787878788283}, {"key": "topic-event_name|40", "value": 0.0037878787878788283}, {"key": "event_name|ICMP: Timestamp Probe", "value": 2.0}, {"key": "entropy|event_name", "value": 1.0549201679861442}], "time": ["2015-04-24T09:00:00Z", "2015-04-24T10:00:00Z"], "anomaly": 0.95596715009610345, "row": ["10.0.0.125", "192.168.0.158", "NSTNORXNUSNAVO"]}}]}}
